blindpay/__init__.py
blindpay/client.py
blindpay/types.py
blindpay/_internal/__init__.py
blindpay/_internal/api_client.py
blindpay/_internal/exceptions.py
blindpay/resources/__init__.py
blindpay/resources/api_keys/__init__.py
blindpay/resources/api_keys/api_keys.py
blindpay/resources/available/__init__.py
blindpay/resources/available/available.py
blindpay/resources/bank_accounts/__init__.py
blindpay/resources/bank_accounts/bank_accounts.py
blindpay/resources/instances/__init__.py
blindpay/resources/instances/instances.py
blindpay/resources/partner_fees/__init__.py
blindpay/resources/partner_fees/partner_fees.py
blindpay/resources/payins/__init__.py
blindpay/resources/payins/payins.py
blindpay/resources/payins/quotes.py
blindpay/resources/payouts/__init__.py
blindpay/resources/payouts/payouts.py
blindpay/resources/quotes/__init__.py
blindpay/resources/quotes/quotes.py
blindpay/resources/receivers/__init__.py
blindpay/resources/receivers/receivers.py
blindpay/resources/terms_of_service/__init__.py
blindpay/resources/terms_of_service/terms_of_service.py
blindpay/resources/virtual_accounts/__init__.py
blindpay/resources/virtual_accounts/virtual_accounts.py
blindpay/resources/wallets/__init__.py
blindpay/resources/wallets/blockchain.py
blindpay/resources/wallets/offramp.py
blindpay/resources/webhooks/__init__.py
blindpay/resources/webhooks/webhooks.py
blindpay-1.2.0.dist-info/METADATA
blindpay-1.2.0.dist-info/WHEEL
blindpay-1.2.0.dist-info/licenses/LICENSE
blindpay-1.2.0.dist-info/RECORD
